wronai_edge/README.md
wronai_edge/__init__.py
wronai_edge/benchmark.py
wronai_edge/cli/__init__.py
wronai_edge/cli/benchmark.py
wronai_edge/cli/main.py
wronai_edge/cli.py
wronai_edge/converters/__init__.py
wronai_edge-0.1.6.dist-info/LICENSE
wronai_edge-0.1.6.dist-info/METADATA
wronai_edge-0.1.6.dist-info/WHEEL
wronai_edge-0.1.6.dist-info/RECORD
