Metadata-Version: 2.3
Name: wronai-edge
Version: 0.1.6
Summary: Edge AI deployment and management tools
License: Apache
Author: Your Name
Author-email: your.email@example.com
Requires-Python: >=3.9,<3.12
Classifier: License :: Other/Proprietary License
Classifier: Programming Language :: Python :: 3
Classifier: Programming Language :: Python :: 3.9
Classifier: Programming Language :: Python :: 3.10
Classifier: Programming Language :: Python :: 3.11
Provides-Extra: all
Provides-Extra: tensorflow
Provides-Extra: torch
Requires-Dist: click (>=8.1.3,<9.0.0)
Requires-Dist: numpy (>=1.24.0,<2.0.0)
Requires-Dist: onnx (>=1.14.0,<2.0.0)
Requires-Dist: onnxruntime (>=1.16.0,<2.0.0)
Requires-Dist: pydantic (>=2.0.0,<3.0.0)
Requires-Dist: rich (>=13.4.2,<14.0.0)
Requires-Dist: tensorflow (>=2.13.0,<3.0.0) ; extra == "tensorflow" or extra == "all"
Requires-Dist: tf2onnx (>=1.14.0,<2.0.0) ; extra == "tensorflow" or extra == "all"
Requires-Dist: torch (>=2.0.0,<3.0.0) ; extra == "torch" or extra == "all"
Requires-Dist: torchvision (>=0.15.0,<0.16.0) ; extra == "torch" or extra == "all"
